ai_pdb/__init__.py
ai_pdb/ai_pdb.py
ai_pdb/formatters.py
ai_pdb/spinner.py
ai_pdb/strings.py
ai_pdb/types.py
ai_pdb-0.1.1.dist-info/LICENSE
ai_pdb-0.1.1.dist-info/METADATA
ai_pdb-0.1.1.dist-info/WHEEL
ai_pdb-0.1.1.dist-info/RECORD
