Metadata-Version: 2.1
Name: ai-pdb
Version: 0.1.1
Summary: The Python Debugger (PDb) augmented with AI.
Author: Daniel Infante Vargas
Author-email: daninfpj@gmail.com
Requires-Python: >=3.8,<4.0
Classifier: Programming Language :: Python :: 3
Classifier: Programming Language :: Python :: 3.8
Classifier: Programming Language :: Python :: 3.9
Classifier: Programming Language :: Python :: 3.10
Classifier: Programming Language :: Python :: 3.11
Classifier: Programming Language :: Python :: 3.12
Requires-Dist: anthropic (>=0.30.1,<0.31.0)
